logrus/__init__.py
logrus/cli.py
logrus/time.py
logrus/utils.py
logrus-0.2.31.dist-info/DESCRIPTION.rst
logrus-0.2.31.dist-info/METADATA
logrus-0.2.31.dist-info/RECORD
logrus-0.2.31.dist-info/WHEEL
logrus-0.2.31.dist-info/entry_points.txt
logrus-0.2.31.dist-info/metadata.json
logrus-0.2.31.dist-info/top_level.txt
