Metadata-Version: 2.0
Name: logrus
Version: 0.2.31
Summary: The Logrus is a collection of random utility functions
Home-page: https://github.com/unixorn/logrus
Author: Joe Block
Author-email: jpb@unixorn.net
License: UNKNOWN
Download-URL: https://github.com/unixorn/logrus/tarball/0.2.31
Keywords: devops,utility
Platform: UNKNOWN
Classifier: Development Status :: 3 - Alpha
Classifier: Operating System :: POSIX
Classifier: License :: OSI Approved :: Apache Software License
Classifier: Programming Language :: Python :: 2.6
Classifier: Topic :: Software Development :: Libraries :: Python Modules
